lightcycler/__init__.py
lightcycler/__pkginfo__.py
lightcycler/gui/__init__.py
lightcycler/gui/dialogs/__init__.py
lightcycler/gui/dialogs/ct_power_dialog.py
lightcycler/gui/dialogs/group_contents_dialog.py
lightcycler/gui/dialogs/grubbs_data_dialog.py
lightcycler/gui/dialogs/means_and_errors_dialog.py
lightcycler/gui/main_windows/__init__.py
lightcycler/gui/main_windows/main_window.py
lightcycler/gui/views/__init__.py
lightcycler/gui/views/copy_pastable_tableview.py
lightcycler/gui/views/droppable_listview.py
lightcycler/gui/views/group_contents_tableview.py
lightcycler/gui/views/groups_listview.py
lightcycler/gui/views/rawdata_tableview.py
lightcycler/gui/widgets/__init__.py
lightcycler/gui/widgets/checkable_combobox.py
lightcycler/gui/widgets/dynamic_matrix_widget.py
lightcycler/gui/widgets/gene_dataframe_widget.py
lightcycler/gui/widgets/genes_widget.py
lightcycler/gui/widgets/groups_widget.py
lightcycler/gui/widgets/logger_widget.py
lightcycler/gui/widgets/rawdata_widget.py
lightcycler/icons/lightcycler.png
lightcycler/kernel/__init__.py
lightcycler/kernel/models/__init__.py
lightcycler/kernel/models/available_genes_model.py
lightcycler/kernel/models/available_samples_model.py
lightcycler/kernel/models/diff_data_model.py
lightcycler/kernel/models/droppable_model.py
lightcycler/kernel/models/dynamic_matrix_model.py
lightcycler/kernel/models/exportable_data_model.py
lightcycler/kernel/models/genes_model.py
lightcycler/kernel/models/group_contents_model.py
lightcycler/kernel/models/groups_model.py
lightcycler/kernel/models/grubbs_data_model.py
lightcycler/kernel/models/n_values_data_model.py
lightcycler/kernel/models/pandas_data_model.py
lightcycler/kernel/models/pvalues_data_model.py
lightcycler/kernel/models/rawdata_model.py
lightcycler/kernel/models/stds_data_model.py
lightcycler/kernel/utils/__init__.py
lightcycler/kernel/utils/progress_bar.py
lightcycler-0.0.18.data/scripts/lightcycler
lightcycler-0.0.18.dist-info/LICENSE
lightcycler-0.0.18.dist-info/METADATA
lightcycler-0.0.18.dist-info/WHEEL
lightcycler-0.0.18.dist-info/top_level.txt
lightcycler-0.0.18.dist-info/RECORD
